[
    {
        "Julia": "1.11.5",
        "BenchmarkTools": {
            "major": 1,
            "minor": 6,
            "patch": 0,
            "prerelease": [],
            "build": []
        }
    },
    [
        [
            "BenchmarkGroup",
            {
                "data": {
                    "run_model": [
                        "BenchmarkGroup",
                        {
                            "data": {
                                "NE-2h-susd-tight": [
                                    "Trial",
                                    {
                                        "allocs": 5410850,
                                        "gctimes": [
                                            5.2214987e7,
                                            5.8099973e7,
                                            9.9222734e7,
                                            7.0889576e7,
                                            1.37439482e8,
                                            5.1863967e7,
                                            6.9459357e7,
                                            5.2304576e7,
                                            7.8777869e7,
                                            1.11041009e8,
                                            1.79642603e8,
                                            7.9626592e7,
                                            5.6645516e7,
                                            1.22052441e8,
                                            1.122466e8,
                                            1.64941689e8,
                                            2.6590703e7,
                                            8.2538429e7,
                                            7.5942215e7,
                                            8.8523786e7
                                        ],
                                        "memory": 244073728,
                                        "params": [
                                            "Parameters",
                                            {
                                                "gctrial": true,
                                                "time_tolerance": 0.05,
                                                "evals_set": false,
                                                "samples": 20,
                                                "evals": 1,
                                                "gcsample": false,
                                                "seconds": 86400.0,
                                                "overhead": 0.0,
                                                "memory_tolerance": 0.01
                                            }
                                        ],
                                        "times": [
                                            3.016005772e10,
                                            3.2206683085e10,
                                            2.9831704359e10,
                                            3.0465930649e10,
                                            3.2385455239e10,
                                            3.5187813247e10,
                                            3.0522586801e10,
                                            3.1607683234e10,
                                            3.1786643273e10,
                                            3.1991558942e10,
                                            3.4493954935e10,
                                            3.1559358082e10,
                                            3.095022235e10,
                                            3.3376355161e10,
                                            3.0765234353e10,
                                            3.311544623e10,
                                            2.968331359e10,
                                            3.4639720125e10,
                                            3.441959763e10,
                                            2.9071324383e10
                                        ]
                                    }
                                ],
                                "NE-1h-basic": [
                                    "Trial",
                                    {
                                        "allocs": 11528716,
                                        "gctimes": [
                                            2.4481781e8,
                                            2.1274274e8,
                                            1.84728489e8,
                                            2.79607089e8,
                                            2.5348018e8,
                                            2.49035557e8,
                                            2.47650526e8,
                                            2.55402349e8,
                                            2.41789531e8,
                                            2.42682014e8,
                                            2.48694264e8,
                                            2.30505213e8,
                                            2.81412198e8,
                                            2.67365876e8,
                                            2.31539149e8,
                                            2.51061369e8,
                                            2.03403647e8,
                                            2.25041018e8,
                                            2.75760466e8,
                                            2.36012944e8
                                        ],
                                        "memory": 441608040,
                                        "params": [
                                            "Parameters",
                                            {
                                                "gctrial": true,
                                                "time_tolerance": 0.05,
                                                "evals_set": false,
                                                "samples": 20,
                                                "evals": 1,
                                                "gcsample": false,
                                                "seconds": 86400.0,
                                                "overhead": 0.0,
                                                "memory_tolerance": 0.01
                                            }
                                        ],
                                        "times": [
                                            7.8510724653e10,
                                            7.3949631535e10,
                                            7.5954245901e10,
                                            7.4018688212e10,
                                            7.6123383621e10,
                                            7.2921433496e10,
                                            8.0248918339e10,
                                            7.5973164665e10,
                                            7.7095333377e10,
                                            8.3400307722e10,
                                            7.9998527554e10,
                                            7.8967569945e10,
                                            7.9323231833e10,
                                            7.8635108974e10,
                                            7.6271564457e10,
                                            7.7069147662e10,
                                            7.5828617061e10,
                                            8.2698051607e10,
                                            8.1776352751e10,
                                            7.6142948111e10
                                        ]
                                    }
                                ],
                                "NE-1h-susd-tight": [
                                    "Trial",
                                    {
                                        "allocs": 17723315,
                                        "gctimes": [
                                            3.61984932e8,
                                            1.91167701e8,
                                            1.8604185e8,
                                            4.76099231e8,
                                            2.3179202e8,
                                            4.41364327e8,
                                            2.57925157e8,
                                            4.60137684e8,
                                            2.60448492e8,
                                            2.42245429e8,
                                            3.34460167e8,
                                            3.32285681e8,
                                            4.29623473e8,
                                            2.23265971e8,
                                            3.93680837e8,
                                            2.39456531e8,
                                            3.51659772e8,
                                            5.16085411e8,
                                            2.79817944e8,
                                            2.57928293e8
                                        ],
                                        "memory": 633060744,
                                        "params": [
                                            "Parameters",
                                            {
                                                "gctrial": true,
                                                "time_tolerance": 0.05,
                                                "evals_set": false,
                                                "samples": 20,
                                                "evals": 1,
                                                "gcsample": false,
                                                "seconds": 86400.0,
                                                "overhead": 0.0,
                                                "memory_tolerance": 0.01
                                            }
                                        ],
                                        "times": [
                                            1.18181900503e11,
                                            1.24047795096e11,
                                            1.23836859989e11,
                                            1.20878087966e11,
                                            1.3024615657e11,
                                            1.32364751936e11,
                                            1.11518516688e11,
                                            1.2528534991e11,
                                            1.2631336335e11,
                                            1.14763415368e11,
                                            1.12948914578e11,
                                            1.21305706848e11,
                                            1.27786563738e11,
                                            1.27393877316e11,
                                            1.34584191189e11,
                                            1.22494409867e11,
                                            1.19122171568e11,
                                            1.25748024012e11,
                                            1.24293816994e11,
                                            1.18621232881e11
                                        ]
                                    }
                                ],
                                "NE-4h-susd-tight": [
                                    "Trial",
                                    {
                                        "allocs": 1955114,
                                        "gctimes": [
                                            4.8778142e7,
                                            2.711634e7,
                                            5.4090604e7,
                                            1.7887083e7,
                                            2.5839224e7,
                                            3.0308963e7,
                                            1.8339785e7,
                                            1.234865e7,
                                            3.6187822e7,
                                            3.7507292e7,
                                            3.6948757e7,
                                            1.1896765e7,
                                            1.7482024e7,
                                            1.7182041e7,
                                            1.7411633e7,
                                            1.5274582e7,
                                            2.2165551e7,
                                            4.0507548e7,
                                            3.5118151e7,
                                            2.6912029e7
                                        ],
                                        "memory": 99769752,
                                        "params": [
                                            "Parameters",
                                            {
                                                "gctrial": true,
                                                "time_tolerance": 0.05,
                                                "evals_set": false,
                                                "samples": 20,
                                                "evals": 1,
                                                "gcsample": false,
                                                "seconds": 86400.0,
                                                "overhead": 0.0,
                                                "memory_tolerance": 0.01
                                            }
                                        ],
                                        "times": [
                                            8.943319561e9,
                                            9.620515102e9,
                                            9.825787861e9,
                                            1.0555326475e10,
                                            9.261591447e9,
                                            1.0114847927e10,
                                            9.456390044e9,
                                            9.480025176e9,
                                            1.0173586794e10,
                                            9.502633953e9,
                                            1.034164581e10,
                                            9.11001352e9,
                                            8.637755804e9,
                                            8.849030826e9,
                                            9.491707517e9,
                                            1.0175785652e10,
                                            1.058561976e10,
                                            9.773777298e9,
                                            9.578107391e9,
                                            1.0065012986e10
                                        ]
                                    }
                                ],
                                "NE-geographically-decreasing-basic": [
                                    "Trial",
                                    {
                                        "allocs": 3703398,
                                        "gctimes": [
                                            7.2714145e7,
                                            2.1141419e7,
                                            4.4695775e7,
                                            2.6664953e7,
                                            8.9693353e7,
                                            6.6512139e7,
                                            1.55207541e8,
                                            5.7689651e7,
                                            5.2010694e7,
                                            1.56699048e8,
                                            1.73284688e8,
                                            4.8199508e7,
                                            8.3735583e7,
                                            4.4171223e7,
                                            4.6554942e7,
                                            1.9346304e7,
                                            4.6532088e7,
                                            6.6412046e7,
                                            1.24763884e8,
                                            4.7603225e7
                                        ],
                                        "memory": 181504752,
                                        "params": [
                                            "Parameters",
                                            {
                                                "gctrial": true,
                                                "time_tolerance": 0.05,
                                                "evals_set": false,
                                                "samples": 20,
                                                "evals": 1,
                                                "gcsample": false,
                                                "seconds": 86400.0,
                                                "overhead": 0.0,
                                                "memory_tolerance": 0.01
                                            }
                                        ],
                                        "times": [
                                            2.4558734027e10,
                                            2.3651284051e10,
                                            2.2891488716e10,
                                            2.3737520175e10,
                                            2.5166264002e10,
                                            2.481525547e10,
                                            2.2859057654e10,
                                            2.2581946398e10,
                                            2.3602485677e10,
                                            2.2798836124e10,
                                            2.3619790855e10,
                                            2.2127116555e10,
                                            2.5313869689e10,
                                            2.2803863399e10,
                                            2.4018116405e10,
                                            2.5139622332e10,
                                            2.2736881462e10,
                                            2.4965692876e10,
                                            2.3000840956e10,
                                            2.2020440739e10
                                        ]
                                    }
                                ],
                                "NE-4h-basic": [
                                    "Trial",
                                    {
                                        "allocs": 1763374,
                                        "gctimes": [
                                            1.5177779e7,
                                            1.4378183e7,
                                            1.661226e7,
                                            2.9481601e7,
                                            1.7698688e7,
                                            1.4479833e7,
                                            8.7320841e7,
                                            0.0,
                                            2.4198199e7,
                                            1.4718884e7,
                                            8.9183423e7,
                                            0.0,
                                            1.9653953e7,
                                            2.0304168e7,
                                            4.9799736e7,
                                            1.5332579e7,
                                            3.3472499e7,
                                            1.692067e7,
                                            1.5907543e7,
                                            4.7343066e7
                                        ],
                                        "memory": 90414000,
                                        "params": [
                                            "Parameters",
                                            {
                                                "gctrial": true,
                                                "time_tolerance": 0.05,
                                                "evals_set": false,
                                                "samples": 20,
                                                "evals": 1,
                                                "gcsample": false,
                                                "seconds": 86400.0,
                                                "overhead": 0.0,
                                                "memory_tolerance": 0.01
                                            }
                                        ],
                                        "times": [
                                            9.784466125e9,
                                            9.177825235e9,
                                            1.019846959e10,
                                            8.833795178e9,
                                            1.0105880671e10,
                                            1.0658700836e10,
                                            1.0259224392e10,
                                            9.256413425e9,
                                            1.1179998688e10,
                                            9.193449903e9,
                                            9.699657605e9,
                                            1.0387710973e10,
                                            1.0155174454e10,
                                            1.0599030969e10,
                                            9.595287055e9,
                                            9.872697154e9,
                                            9.400899779e9,
                                            9.608082544e9,
                                            8.628493623e9,
                                            1.0884481328e10
                                        ]
                                    }
                                ],
                                "NE-2h-basic": [
                                    "Trial",
                                    {
                                        "allocs": 4934894,
                                        "gctimes": [
                                            1.4019719e8,
                                            1.26800177e8,
                                            7.1168668e7,
                                            6.3163725e7,
                                            4.8853294e7,
                                            7.0271463e7,
                                            4.3853955e7,
                                            5.6496357e7,
                                            5.4535366e7,
                                            7.2519082e7,
                                            2.2498891e7,
                                            4.9253817e7,
                                            4.4297939e7,
                                            4.926993e7,
                                            1.02068318e8,
                                            5.1322142e7,
                                            4.5166967e7,
                                            4.704722e7,
                                            6.9939564e7,
                                            4.2979084e7
                                        ],
                                        "memory": 204863664,
                                        "params": [
                                            "Parameters",
                                            {
                                                "gctrial": true,
                                                "time_tolerance": 0.05,
                                                "evals_set": false,
                                                "samples": 20,
                                                "evals": 1,
                                                "gcsample": false,
                                                "seconds": 86400.0,
                                                "overhead": 0.0,
                                                "memory_tolerance": 0.01
                                            }
                                        ],
                                        "times": [
                                            3.1191386177e10,
                                            2.9356103413e10,
                                            2.9007248542e10,
                                            2.9839672324e10,
                                            3.245901665e10,
                                            2.919447857e10,
                                            2.9218015239e10,
                                            3.037727488e10,
                                            3.1289289898e10,
                                            2.9908582663e10,
                                            2.8897381781e10,
                                            2.8508329692e10,
                                            2.9113414432e10,
                                            2.5580143415e10,
                                            3.0533021047e10,
                                            3.2237090111e10,
                                            3.0314704279e10,
                                            2.5470116378e10,
                                            3.006279935e10,
                                            2.5995967848e10
                                        ]
                                    }
                                ],
                                "NE-geographically-decreasing-susd-tight": [
                                    "Trial",
                                    {
                                        "allocs": 5260219,
                                        "gctimes": [
                                            6.308269e7,
                                            5.9826476e7,
                                            5.6002173e7,
                                            6.4292864e7,
                                            8.5068009e7,
                                            9.1566535e7,
                                            5.9009253e7,
                                            9.0137377e7,
                                            1.85453332e8,
                                            1.33008278e8,
                                            8.6087478e7,
                                            7.2730301e7,
                                            7.7704542e7,
                                            5.2510703e7,
                                            1.70060615e8,
                                            3.6202311e7,
                                            5.3704366e7,
                                            6.8300111e7,
                                            5.7504937e7,
                                            7.2273508e7
                                        ],
                                        "memory": 237067064,
                                        "params": [
                                            "Parameters",
                                            {
                                                "gctrial": true,
                                                "time_tolerance": 0.05,
                                                "evals_set": false,
                                                "samples": 20,
                                                "evals": 1,
                                                "gcsample": false,
                                                "seconds": 86400.0,
                                                "overhead": 0.0,
                                                "memory_tolerance": 0.01
                                            }
                                        ],
                                        "times": [
                                            2.9864019509e10,
                                            3.1382297725e10,
                                            2.839376987e10,
                                            3.0964427501e10,
                                            2.8663613229e10,
                                            3.0247282641e10,
                                            3.015671319e10,
                                            3.0707496125e10,
                                            3.0905312079e10,
                                            3.0709727888e10,
                                            2.8984471997e10,
                                            3.0603911208e10,
                                            2.7094219265e10,
                                            3.1839608918e10,
                                            2.8596554796e10,
                                            2.8887467133e10,
                                            3.0436055517e10,
                                            3.1412368268e10,
                                            3.0366029067e10,
                                            3.06320361e10
                                        ]
                                    }
                                ]
                            },
                            "tags": []
                        }
                    ],
                    "create_model": [
                        "BenchmarkGroup",
                        {
                            "data": {
                                "NE-2h-susd-tight": [
                                    "Trial",
                                    {
                                        "allocs": 19846486,
                                        "gctimes": [
                                            2.48820547e8,
                                            3.57142058e8,
                                            3.35834969e8,
                                            2.53984347e8,
                                            4.34363065e8,
                                            3.19169067e8,
                                            3.94652392e8,
                                            2.12908834e8,
                                            3.89396911e8,
                                            3.86856112e8,
                                            3.44877591e8,
                                            3.89125048e8,
                                            1.91803762e8,
                                            3.83217826e8,
                                            3.2545631e8,
                                            2.61366771e8,
                                            4.19137317e8,
                                            3.36984094e8,
                                            3.70129297e8,
                                            2.55990122e8
                                        ],
                                        "memory": 1267085856,
                                        "params": [
                                            "Parameters",
                                            {
                                                "gctrial": true,
                                                "time_tolerance": 0.05,
                                                "evals_set": false,
                                                "samples": 20,
                                                "evals": 1,
                                                "gcsample": false,
                                                "seconds": 86400.0,
                                                "overhead": 0.0,
                                                "memory_tolerance": 0.01
                                            }
                                        ],
                                        "times": [
                                            3.619259411e9,
                                            3.727015817e9,
                                            3.781942078e9,
                                            3.673374893e9,
                                            3.942090124e9,
                                            3.750726089e9,
                                            3.929485023e9,
                                            3.687609081e9,
                                            3.916383187e9,
                                            3.889451447e9,
                                            3.806394971e9,
                                            3.910196857e9,
                                            3.656751106e9,
                                            3.944743783e9,
                                            3.845054211e9,
                                            3.718883855e9,
                                            3.910046854e9,
                                            3.805018721e9,
                                            3.873621136e9,
                                            3.68858305e9
                                        ]
                                    }
                                ],
                                "NE-1h-basic": [
                                    "Trial",
                                    {
                                        "allocs": 29459763,
                                        "gctimes": [
                                            3.83967497e8,
                                            4.45045338e8,
                                            4.45576353e8,
                                            4.24782417e8,
                                            4.13140424e8,
                                            3.38991354e8,
                                            3.84319265e8,
                                            4.10723505e8,
                                            5.02372419e8,
                                            3.12429494e8,
                                            4.09552167e8,
                                            4.15702442e8,
                                            5.34015038e8,
                                            4.55508389e8,
                                            4.58752481e8,
                                            3.58095694e8,
                                            5.79478335e8,
                                            4.25955602e8,
                                            4.42016878e8,
                                            5.18662314e8
                                        ],
                                        "memory": 1780959728,
                                        "params": [
                                            "Parameters",
                                            {
                                                "gctrial": true,
                                                "time_tolerance": 0.05,
                                                "evals_set": false,
                                                "samples": 20,
                                                "evals": 1,
                                                "gcsample": false,
                                                "seconds": 86400.0,
                                                "overhead": 0.0,
                                                "memory_tolerance": 0.01
                                            }
                                        ],
                                        "times": [
                                            3.802491441e9,
                                            3.849603669e9,
                                            3.867754139e9,
                                            3.932110395e9,
                                            3.883204293e9,
                                            3.786117689e9,
                                            3.816101744e9,
                                            3.971707822e9,
                                            4.072644238e9,
                                            3.82743458e9,
                                            3.829498094e9,
                                            3.971435283e9,
                                            4.062514131e9,
                                            3.941547569e9,
                                            3.964467587e9,
                                            3.798772701e9,
                                            4.089726051e9,
                                            3.94862768e9,
                                            4.012049328e9,
                                            4.090751597e9
                                        ]
                                    }
                                ],
                                "NE-1h-susd-tight": [
                                    "Trial",
                                    {
                                        "allocs": 40423185,
                                        "gctimes": [
                                            4.99755771e8,
                                            6.7263455e8,
                                            6.81813592e8,
                                            6.78463104e8,
                                            4.55159157e8,
                                            5.93473032e8,
                                            6.7054339e8,
                                            7.10214994e8,
                                            6.37748239e8,
                                            6.68747101e8,
                                            6.50113475e8,
                                            5.15810344e8,
                                            8.68969453e8,
                                            6.76924316e8,
                                            7.67951722e8,
                                            6.36854179e8,
                                            7.44074685e8,
                                            6.98655573e8,
                                            5.96510028e8,
                                            6.65434371e8
                                        ],
                                        "memory": 2558222240,
                                        "params": [
                                            "Parameters",
                                            {
                                                "gctrial": true,
                                                "time_tolerance": 0.05,
                                                "evals_set": false,
                                                "samples": 20,
                                                "evals": 1,
                                                "gcsample": false,
                                                "seconds": 86400.0,
                                                "overhead": 0.0,
                                                "memory_tolerance": 0.01
                                            }
                                        ],
                                        "times": [
                                            5.495806162e9,
                                            5.628749288e9,
                                            5.639746228e9,
                                            5.795492562e9,
                                            5.526664341e9,
                                            5.629226676e9,
                                            5.916863663e9,
                                            5.855213139e9,
                                            5.764339475e9,
                                            5.864292618e9,
                                            5.898337591e9,
                                            5.703058053e9,
                                            6.068779926e9,
                                            5.924631891e9,
                                            5.874122116e9,
                                            5.872809051e9,
                                            5.906563562e9,
                                            5.82728656e9,
                                            5.789700808e9,
                                            5.90592418e9
                                        ]
                                    }
                                ],
                                "NE-4h-susd-tight": [
                                    "Trial",
                                    {
                                        "allocs": 10023809,
                                        "gctimes": [
                                            1.27465416e8,
                                            1.86810525e8,
                                            1.37220212e8,
                                            1.74329565e8,
                                            2.34327257e8,
                                            1.44381179e8,
                                            1.91131777e8,
                                            1.65784058e8,
                                            1.24639452e8,
                                            1.12146517e8,
                                            1.59359277e8,
                                            2.02806549e8,
                                            1.04656814e8,
                                            1.9026957e8,
                                            2.03641187e8,
                                            1.73149883e8,
                                            1.12927659e8,
                                            1.58339058e8,
                                            2.02908329e8,
                                            1.03009302e8
                                        ],
                                        "memory": 664871320,
                                        "params": [
                                            "Parameters",
                                            {
                                                "gctrial": true,
                                                "time_tolerance": 0.05,
                                                "evals_set": false,
                                                "samples": 20,
                                                "evals": 1,
                                                "gcsample": false,
                                                "seconds": 86400.0,
                                                "overhead": 0.0,
                                                "memory_tolerance": 0.01
                                            }
                                        ],
                                        "times": [
                                            2.813075853e9,
                                            2.860472226e9,
                                            2.793142763e9,
                                            2.918086258e9,
                                            2.957296765e9,
                                            2.812670873e9,
                                            2.940706691e9,
                                            2.824823487e9,
                                            2.796933885e9,
                                            2.808968289e9,
                                            2.832969867e9,
                                            2.920269154e9,
                                            2.809873852e9,
                                            2.95436922e9,
                                            2.961080992e9,
                                            2.92042811e9,
                                            2.781307002e9,
                                            2.821483428e9,
                                            2.920141404e9,
                                            2.79541006e9
                                        ]
                                    }
                                ],
                                "NE-geographically-decreasing-basic": [
                                    "Trial",
                                    {
                                        "allocs": 15163383,
                                        "gctimes": [
                                            1.88485677e8,
                                            2.21832719e8,
                                            2.69224582e8,
                                            1.90064608e8,
                                            2.3216485e8,
                                            2.96046862e8,
                                            2.29852422e8,
                                            1.58095926e8,
                                            2.69419782e8,
                                            2.29856831e8,
                                            2.62945791e8,
                                            3.17977586e8,
                                            1.69821479e8,
                                            2.37768852e8,
                                            1.84284461e8,
                                            2.37778703e8,
                                            1.77889621e8,
                                            2.39423035e8,
                                            1.77316526e8,
                                            2.15226214e8
                                        ],
                                        "memory": 927555848,
                                        "params": [
                                            "Parameters",
                                            {
                                                "gctrial": true,
                                                "time_tolerance": 0.05,
                                                "evals_set": false,
                                                "samples": 20,
                                                "evals": 1,
                                                "gcsample": false,
                                                "seconds": 86400.0,
                                                "overhead": 0.0,
                                                "memory_tolerance": 0.01
                                            }
                                        ],
                                        "times": [
                                            2.545513008e9,
                                            2.582066176e9,
                                            2.712205909e9,
                                            2.589978356e9,
                                            2.69092013e9,
                                            2.76856512e9,
                                            2.657927219e9,
                                            2.59242262e9,
                                            2.764927319e9,
                                            2.721196993e9,
                                            2.819051713e9,
                                            2.808044925e9,
                                            2.566097259e9,
                                            2.616870667e9,
                                            2.563557597e9,
                                            2.607755074e9,
                                            2.558747138e9,
                                            2.651540347e9,
                                            2.552017583e9,
                                            2.61147626e9
                                        ]
                                    }
                                ],
                                "NE-4h-basic": [
                                    "Trial",
                                    {
                                        "allocs": 7778378,
                                        "gctimes": [
                                            5.1641996e7,
                                            1.15783431e8,
                                            1.29382339e8,
                                            1.45773639e8,
                                            6.1112e7,
                                            1.461127e8,
                                            1.34050026e8,
                                            8.7887372e7,
                                            1.21641448e8,
                                            1.26025012e8,
                                            1.54613985e8,
                                            8.3084664e7,
                                            1.37532832e8,
                                            1.48665049e8,
                                            6.1398703e7,
                                            1.38178837e8,
                                            1.41045251e8,
                                            8.3473778e7,
                                            1.37758304e8,
                                            1.29695369e8
                                        ],
                                        "memory": 487489960,
                                        "params": [
                                            "Parameters",
                                            {
                                                "gctrial": true,
                                                "time_tolerance": 0.05,
                                                "evals_set": false,
                                                "samples": 20,
                                                "evals": 1,
                                                "gcsample": false,
                                                "seconds": 86400.0,
                                                "overhead": 0.0,
                                                "memory_tolerance": 0.01
                                            }
                                        ],
                                        "times": [
                                            1.937736964e9,
                                            2.040372222e9,
                                            2.053559936e9,
                                            2.107817802e9,
                                            1.945681225e9,
                                            2.088739751e9,
                                            2.078033586e9,
                                            1.971021333e9,
                                            2.058826224e9,
                                            2.085585464e9,
                                            2.092537158e9,
                                            1.995896437e9,
                                            2.067255847e9,
                                            2.094732523e9,
                                            1.995940534e9,
                                            2.082775268e9,
                                            2.078837247e9,
                                            2.000684222e9,
                                            2.081203124e9,
                                            2.05026204e9
                                        ]
                                    }
                                ],
                                "NE-2h-basic": [
                                    "Trial",
                                    {
                                        "allocs": 15005626,
                                        "gctimes": [
                                            1.72240604e8,
                                            2.41149387e8,
                                            3.18604386e8,
                                            2.37526208e8,
                                            1.93953776e8,
                                            3.51519874e8,
                                            2.80092563e8,
                                            1.54565775e8,
                                            2.64128477e8,
                                            2.54017998e8,
                                            3.04675916e8,
                                            2.88381588e8,
                                            1.77782999e8,
                                            3.09612585e8,
                                            2.32656978e8,
                                            1.45993799e8,
                                            2.27060994e8,
                                            2.94916621e8,
                                            2.69786109e8,
                                            1.57048253e8
                                        ],
                                        "memory": 913869336,
                                        "params": [
                                            "Parameters",
                                            {
                                                "gctrial": true,
                                                "time_tolerance": 0.05,
                                                "evals_set": false,
                                                "samples": 20,
                                                "evals": 1,
                                                "gcsample": false,
                                                "seconds": 86400.0,
                                                "overhead": 0.0,
                                                "memory_tolerance": 0.01
                                            }
                                        ],
                                        "times": [
                                            2.522137291e9,
                                            2.603256919e9,
                                            2.716247965e9,
                                            2.613722849e9,
                                            2.577379233e9,
                                            2.785032895e9,
                                            2.680864725e9,
                                            2.57853067e9,
                                            2.707230401e9,
                                            2.754120628e9,
                                            2.748158701e9,
                                            2.731082966e9,
                                            2.59171531e9,
                                            2.774160074e9,
                                            2.649102759e9,
                                            2.550308422e9,
                                            2.680794748e9,
                                            2.736870477e9,
                                            2.692456128e9,
                                            2.573987655e9
                                        ]
                                    }
                                ],
                                "NE-geographically-decreasing-susd-tight": [
                                    "Trial",
                                    {
                                        "allocs": 19964753,
                                        "gctimes": [
                                            3.2811011e8,
                                            3.40560586e8,
                                            3.83298339e8,
                                            3.78691093e8,
                                            3.56682895e8,
                                            2.41276439e8,
                                            4.39248063e8,
                                            3.37569551e8,
                                            2.78753496e8,
                                            3.03886435e8,
                                            3.83065953e8,
                                            1.96613591e8,
                                            3.72007164e8,
                                            4.39318306e8,
                                            3.1488203e8,
                                            3.37759082e8,
                                            2.61711768e8,
                                            2.85054652e8,
                                            3.60787343e8,
                                            3.18190956e8
                                        ],
                                        "memory": 1276086832,
                                        "params": [
                                            "Parameters",
                                            {
                                                "gctrial": true,
                                                "time_tolerance": 0.05,
                                                "evals_set": false,
                                                "samples": 20,
                                                "evals": 1,
                                                "gcsample": false,
                                                "seconds": 86400.0,
                                                "overhead": 0.0,
                                                "memory_tolerance": 0.01
                                            }
                                        ],
                                        "times": [
                                            3.730809573e9,
                                            3.710220615e9,
                                            3.865930929e9,
                                            3.849932797e9,
                                            3.835826489e9,
                                            3.703753545e9,
                                            3.885260513e9,
                                            3.803568619e9,
                                            3.853082788e9,
                                            3.769366508e9,
                                            3.845770651e9,
                                            3.684657446e9,
                                            3.901963048e9,
                                            3.927960871e9,
                                            3.859623103e9,
                                            3.833069488e9,
                                            3.772501763e9,
                                            3.695539167e9,
                                            3.811006441e9,
                                            3.81393181e9
                                        ]
                                    }
                                ]
                            },
                            "tags": []
                        }
                    ]
                },
                "tags": []
            }
        ]
    ]
]